pygame_pause/__init__.py
pygame_pause/pause.py
pygame_pause-1.0.0.dist-info/METADATA
pygame_pause-1.0.0.dist-info/WHEEL
pygame_pause-1.0.0.dist-info/top_level.txt
pygame_pause-1.0.0.dist-info/RECORD
