Metadata-Version: 2.1
Name: pygame-pause
Version: 1.0.0
Summary: It game pause module
Home-page: https://github.com/kurban-hussain-786/MY-CODE
Author: kurban hussain
Author-email: kurbanhussain086@gmail.com
License: MIT
Keywords: pause in pygame,pygame pause,pause,game pause,game_pause,pygame_pause,pause_pygame,pause pygame game,pygame,pygame PAUSE,PYGAME PAUSE,PUASE PYGAME
Classifier: License :: OSI Approved :: MIT License
Classifier: Programming Language :: Python :: 3.6
Classifier: Programming Language :: Python :: 3.7
Classifier: Programming Language :: Python :: 3.8
